docs/cli.png
docs/configuration.md
docs/configuration_paths.png
docs/custom_model.md
docs/model_pipeline.md
docs/model_pipeline.png
docs/seizyML.png
docs/train_files.png
docs/verify_gui.png
examples/to_h5.py
seizyml/cli.py
seizyml/config.yaml
seizyml/temp_config.yaml
seizyml/data_preparation/file_check.py
seizyml/data_preparation/get_predictions.py
seizyml/data_preparation/preprocess.py
seizyml/helper/event_match.py
seizyml/helper/features.py
seizyml/helper/get_features.py
seizyml/helper/get_seizure_properties.py
seizyml/helper/io.py
seizyml/helper/progressbar.py
seizyml/tests/test_array_helper.py
seizyml/train/model_settings.py
seizyml/train/select_features.py
seizyml/train/train_models.py
seizyml/user_gui/user_verify.py
seizyml/user_gui/verify_gui.py
seizyml-0.1.0.dist-info/METADATA
seizyml-0.1.0.dist-info/WHEEL
seizyml-0.1.0.dist-info/entry_points.txt
seizyml-0.1.0.dist-info/top_level.txt
seizyml-0.1.0.dist-info/RECORD
