Metadata-Version: 2.2
Name: seizyml
Version: 0.1.0
Summary: A CLI tool for seizure detection using interpretable ML
Author-email: Pantelis Antonoudiou <pantelis.antonoudiou@gmail.com>
Project-URL: Homepage, https://github.com/neurosimata/seizy_ml
Project-URL: Repository, https://github.com/neurosimata/seizy_ml
Requires-Python: <3.10,>=3.9
Requires-Dist: appdirs==1.4.4
Requires-Dist: bottleneck==1.3.5
Requires-Dist: certifi==2023.7.22
Requires-Dist: cffi==1.15.1
Requires-Dist: click==8.1.6
Requires-Dist: colorama==0.4.6
Requires-Dist: cryptography==41.0.2
Requires-Dist: cycler==0.11.0
Requires-Dist: exceptiongroup==1.0.4
Requires-Dist: fonttools==4.25.0
Requires-Dist: idna==3.4
Requires-Dist: joblib==1.2.0
Requires-Dist: kiwisolver==1.4.4
Requires-Dist: matplotlib==3.5.0
Requires-Dist: numba==0.57.0
Requires-Dist: numexpr==2.8.4
Requires-Dist: numpy==1.24.3
Requires-Dist: packaging==23.0
Requires-Dist: pandas==1.5.3
Requires-Dist: pillow==9.4.0
Requires-Dist: pluggy==1.0.0
Requires-Dist: pooch==1.4.0
Requires-Dist: pycparser==2.21
Requires-Dist: pyopenssl==23.2.0
Requires-Dist: pyparsing==3.0.9
Requires-Dist: PyQt5==5.15.7
Requires-Dist: pytest==7.4.0
Requires-Dist: python-dateutil==2.8.2
Requires-Dist: pytz==2022.7
Requires-Dist: requests==2.31.0
Requires-Dist: scikit-learn==1.2.1
Requires-Dist: scipy==1.10.1
Requires-Dist: setuptools==68.0.0
Requires-Dist: six==1.16.0
Requires-Dist: tables==3.8
Requires-Dist: threadpoolctl==2.2.0
Requires-Dist: toml==0.10.2
Requires-Dist: tornado==6.3.2
Requires-Dist: tqdm==4.65.0
Requires-Dist: urllib3==1.26.16
Requires-Dist: pick==2.2.0
Requires-Dist: pyyaml==6.0.1
Requires-Dist: windows-curses==2.3.1
